LICENSE.txt
MANIFEST.in
README.rst
setup.py
cynq/__init__.py
cynq/arm.py
cynq/changeset.py
cynq/controller.py
cynq/error.py
cynq/logging_helper.py
cynq/spec.py
cynq.egg-info/PKG-INFO
cynq.egg-info/SOURCES.txt
cynq.egg-info/dependency_links.txt
cynq.egg-info/requires.txt
cynq.egg-info/top_level.txt
cynq/store/__init__.py
cynq/store/base.py
cynq/store/django.py
cynq/store/facet.py
cynq/store/memory.py
cynq/store/obj.py
cynq/store/voodoo.py
cynq/test/__init__.py
cynq/test/helper.py
cynq/test/logger.py
cynq/test/test.py