Metadata-Version: 1.0
Name: cynq
Version: 2.3.11
Summary: A data synchronizer
Home-page: https://github.com/HubSpot/cynq
Author: prior
Author-email: mprior@hubspot.com
License: LICENSE.txt
Download-URL: https://github.com/HubSpot/cynq/tarball/v2.3.11
Platform: UNKNOWN
